LICENSE.md
README.md
pyproject.toml
src/ewokssphinx/__init__.py
src/ewokssphinx/ewoks_task_directive.py
src/ewokssphinx/ewokssphinx.css
src/ewokssphinx/pydantic_utils.py
src/ewokssphinx/utils.py
src/ewokssphinx.egg-info/PKG-INFO
src/ewokssphinx.egg-info/SOURCES.txt
src/ewokssphinx.egg-info/dependency_links.txt
src/ewokssphinx.egg-info/requires.txt
src/ewokssphinx.egg-info/top_level.txt
src/ewokssphinx/tests/__init__.py
src/ewokssphinx/tests/conftest.py
src/ewokssphinx/tests/dummy_tasks.py
src/ewokssphinx/tests/dummy_tasks_pydantic.py
src/ewokssphinx/tests/test_directive.py
src/ewokssphinx/tests/test_directive_pydantic.py