Metadata-Version: 2.4
Name: ewokssphinx
Version: 1.0.0
Summary: Ewoks Sphinx directives
Author-email: ESRF <dau-pydev@esrf.fr>
License: # MIT License
Project-URL: Homepage, https://gitlab.esrf.fr/workflow/ewoks/ewokssphinx/
Project-URL: Documentation, https://gitlab.esrf.fr/workflow/ewoks/ewokssphinx/-/blob/main/README.md
Project-URL: Repository, https://gitlab.esrf.fr/workflow/ewoks/ewokssphinx/
Project-URL: Issues, https://gitlab.esrf.fr/workflow/ewoks/ewokssphinx/issues
Project-URL: Changelog, https://gitlab.esrf.fr/workflow/ewoks/ewokssphinx/-/blob/main/CHANGELOG.md
Keywords: ewoks,sphinx
Classifier: Intended Audience :: Science/Research
Classifier: License :: OSI Approved :: MIT License
Classifier: Programming Language :: Python :: 3
Classifier: Framework :: Sphinx :: Extension
Requires-Python: >=3.10
License-File: LICENSE.md
Requires-Dist: sphinx
Requires-Dist: ewokscore>=1.3.0
Provides-Extra: test
Requires-Dist: pytest>=7; extra == "test"
Provides-Extra: dev
Requires-Dist: ewokssphinx[test]; extra == "dev"
Requires-Dist: black>=25; extra == "dev"
Requires-Dist: flake8>=4; extra == "dev"
Provides-Extra: doc
Requires-Dist: ewokssphinx[test]; extra == "doc"
Requires-Dist: myst-parser; extra == "doc"
Requires-Dist: pydata_sphinx_theme; extra == "doc"
Requires-Dist: sphinx-design; extra == "doc"
Dynamic: license-file
